pywfn/__init__.py
pywfn/chems.py
pywfn/cli.py
pywfn/config.py
pywfn/editor.py
pywfn/mcp.py
pywfn/utils.py
pywfn/atomprop/__init__.py
pywfn/atomprop/activity.py
pywfn/atomprop/charge.py
pywfn/atomprop/direction.py
pywfn/atomprop/energy.py
pywfn/atomprop/lutils.py
pywfn/base/__init__.py
pywfn/base/atom.py
pywfn/base/basis.py
pywfn/base/bond.py
pywfn/base/coefs.py
pywfn/base/geome.py
pywfn/base/mole.py
pywfn/bondprop/__init__.py
pywfn/bondprop/direction.py
pywfn/bondprop/lutils.py
pywfn/bondprop/order.py
pywfn/bondprop/selectPI.py
pywfn/data/__init__.py
pywfn/data/bastrans.py
pywfn/data/consts.py
pywfn/data/elements.py
pywfn/data/lebedev.py
pywfn/data/march.py
pywfn/data/radDens.py
pywfn/data/temps.py
pywfn/gridprop/__init__.py
pywfn/gridprop/density.py
pywfn/gridprop/dftgrid.py
pywfn/gridprop/hmowfn.py
pywfn/gridprop/lutils.py
pywfn/gridprop/potential.py
pywfn/gridprop/wfnfunc.py
pywfn/maths/__init__.py
pywfn/maths/atom.py
pywfn/maths/flib.dll
pywfn/maths/flib.py
pywfn/maths/march.py
pywfn/maths/mol.py
pywfn/maths/rlib.pyd
pywfn/maths/rlib.so
pywfn/maths/unit.py
pywfn/moleprop/__init__.py
pywfn/moleprop/aromacity.py
pywfn/orbtprop/__init__.py
pywfn/orbtprop/decom.py
pywfn/orbtprop/popul.py
pywfn/reader/__init__.py
pywfn/reader/any.py
pywfn/reader/fch.py
pywfn/reader/gjf.py
pywfn/reader/log.py
pywfn/reader/mod.py
pywfn/reader/mol.py
pywfn/reader/sdf.py
pywfn/reader/utils.py
pywfn/reader/wfn.py
pywfn/reader/xyz.py
pywfn/tools/__init__.py
pywfn/tools/engCorr.py
pywfn/tools/gjf.py
pywfn/tools/log.py
pywfn/tools/logSplitIrc.py
pywfn/tools/xml.py
pywfn/tools/xmlPES.py
pywfn/writer/__init__.py
pywfn/writer/cub.py
pywfn/writer/gjf.py
pywfn/writer/mol.py
pywfn/writer/obj.py
pywfn/writer/xyz.py
pywfn-1.0.7.dist-info/METADATA
pywfn-1.0.7.dist-info/WHEEL
pywfn-1.0.7.dist-info/entry_points.txt
pywfn-1.0.7.dist-info/licenses/LICENSE
pywfn-1.0.7.dist-info/RECORD
