Metadata-Version: 2.4
Name: pywfn
Version: 1.0.7
Summary: A python package for wave function analysis
Project-URL: Homepage, https://github.com/qmlCoder/pywfn
Project-URL: Issues, https://github.com/qmlCoder/pywfn/issues
Author-email: shixiaofei <1103275712@qq.com>
License-Expression: MIT
License-File: LICENSE
Keywords: chemistry,wave function
Classifier: Development Status :: 4 - Beta
Classifier: Operating System :: OS Independent
Classifier: Programming Language :: Fortran
Classifier: Programming Language :: Python :: 3.10
Classifier: Programming Language :: Rust
Requires-Python: >=3.10
Requires-Dist: matplotlib>=3.10.1
Requires-Dist: numpy>=2.2.3
Requires-Dist: rich>=13.9.4
